<?xml version="1.0" encoding="UTF-8"?>
<metadata xml:lang="en"><Esri><CreaDate>20120823</CreaDate><CreaTime>01271200</CreaTime><ArcGISFormat>1.0</ArcGISFormat><SyncOnce>TRUE</SyncOnce><DataProperties><lineage><Process ToolSource="C:\Program Files\ArcGIS\Desktop10.0\ArcToolbox\Toolboxes\Data Management Tools.tbx\CopyRaster" Date="20120823" Time="012723">CopyRaster C:/Users/lfortini/Data/JP_data\cc8 C:\Users\lfortini\Data\JP_data\results\FCE0008.tif LZW # 0 NONE NONE 2_BIT</Process><Process ToolSource="C:\Program Files\ArcGIS\Desktop10.0\ArcToolbox\Toolboxes\Data Management Tools.tbx\BuildRasterAttributeTable" Date="20120823" Time="012747">BuildRasterAttributeTable C:/Users/lfortini/Data/JP_data/results/FCE0008.tif NONE</Process></lineage></DataProperties></Esri></metadata>
